CONTRIBUTING.rst
HISTORY.rst
LICENSE
MANIFEST.in
README.rst
setup.cfg
setup.py
docs/Makefile
docs/conf.py
docs/contributing.rst
docs/history.rst
docs/index.rst
docs/installation.rst
docs/make.bat
docs/readme.rst
docs/usage.rst
dooble/__init__.py
dooble/cli.py
dooble/dooble.py
dooble/idl.py
dooble/marble.py
dooble/render.py
dooble.egg-info/PKG-INFO
dooble.egg-info/SOURCES.txt
dooble.egg-info/dependency_links.txt
dooble.egg-info/entry_points.txt
dooble.egg-info/not-zip-safe
dooble.egg-info/requires.txt
dooble.egg-info/top_level.txt
tests/__init__.py
tests/test_idl.py
tests/test_marble.py