Metadata-Version: 1.1
Name: dooble
Version: 0.7.0
Summary: A marble diagram generator
Home-page: https://github.com/mainro/dooble
Author: Romain Picard
Author-email: romain.picard@oakbits.com
License: MIT license
Keywords: dooble
Platform: UNKNOWN
Classifier: Development Status :: 2 - Pre-Alpha
Classifier: Intended Audience :: Developers
Classifier: License :: OSI Approved :: MIT License
Classifier: Natural Language :: English
Classifier: Programming Language :: Python :: 3
Classifier: Programming Language :: Python :: 3.6
Classifier: Programming Language :: Python :: 3.7
